werkflow_core/__init__.py
werkflow_core/base/__init__.py
werkflow_core/base/module.py
werkflow_core/exceptions/__init__.py
werkflow_core/exceptions/missing_module_error.py
werkflow_core-0.1.6.dist-info/licenses/LICENSE
werkflow_core-0.1.6.dist-info/METADATA
werkflow_core-0.1.6.dist-info/WHEEL
werkflow_core-0.1.6.dist-info/top_level.txt
werkflow_core-0.1.6.dist-info/RECORD
